{
  "generated": "2025-07-04T13:42:22.635Z",
  "count": 4,
  "projects": [
    {
      "name": "golden-path-redesign",
      "title": "Golden Path - Step 2",
      "description": "No description available",
      "path": "./golden-path-redesign/",
      "files": [
        "index.html",
        "styles.css",
        "script.js"
      ],
      "icon": "G",
      "lastModified": "2025-07-04T13:00:20.364Z",
      "type": "UI Component"
    },
    {
      "name": "grammarly-ping-pong",
      "title": "Grammarly Ping Pong",
      "description": "No description available",
      "path": "./grammarly-ping-pong/",
      "files": [
        "index.html",
        "styles.css",
        "script.js"
      ],
      "icon": "G",
      "lastModified": "2025-07-04T13:35:39.963Z",
      "type": "UI Component"
    },
    {
      "name": "my-first-gr-design",
      "title": "Grammarly Style Text Interaction",
      "description": "No description available",
      "path": "./my-first-gr-design/",
      "files": [
        "index.html",
        "styles.css",
        "script.js"
      ],
      "icon": "G",
      "lastModified": "2025-07-04T13:00:20.364Z",
      "type": "UI Component"
    },
    {
      "name": "thinking-grammarly",
      "title": "Thinking Grammarly Prototype",
      "description": "No description available",
      "path": "./thinking-grammarly/",
      "files": [
        "index.html",
        "styles.css",
        "script.js"
      ],
      "icon": "T",
      "lastModified": "2025-07-04T13:23:15.655Z",
      "type": "UI Component"
    }
  ]
}